[
  {
    "start": 12.923,
    "end": 14.486,
    "english": "When I was 27 years old",
    "burmese": "ကျွန်မ အသက် ၂၇ နှစ်အရွယ်တုန်းက"
  },
  {
    "start": 14.506,
    "end": 17.771,
    "english": "I left a very demanding job in management consulting.",
    "burmese": "အရမ်းပင်ပန်းတဲ့ စီမံခန့်ခွဲမှုဆိုင်ရာ အကြံပေးအလုပ်ကနေ ထွက်ခဲ့တယ်။"
  },
  {
    "start": 21.818,
    "end": 27.588,
    "english": "I went to teach seventh graders math in the New York City public schools.",
    "burmese": "နယူးယောက်မြို့မှာရှိတဲ့ အစိုးရကျောင်းတစ်ခုမှာ သတ္တမတန်း ကျောင်းသားတွေကို သင်္ချာသွားသင်ပါတယ်။"
  },
  {
    "start": 28.39,
    "end": 31.014,
    "english": "And like any teacher, I made quizzes and tests.",
    "burmese": "တခြားဆရာမတွေလိုပဲ ကျွန်မလည်း Quiz တွေ၊ စာမေးပွဲတွေ လုပ်ပေးတယ်။"
  },
  {
    "start": 31.335,
    "end": 32.597,
    "english": "I gave out homework assignments.",
    "burmese": "အိမ်စာတွေလည်း ကျွန်မပေးခဲ့တယ်။"
  },
  {
    "start": 33.238,
    "end": 36.163,
    "english": "When the work came back, I calculated grades.",
    "burmese": "အိမ်စာတွေလာထပ်တဲ့အခါ အမှတ်တွေတွက်ပေးတယ်။"
  },
  {
    "start": 38.84,
    "end": 44.272,
    "english": "IQ was not the only difference between my best and my worst students.",
    "burmese": "ကျွန်မရဲ့ အတော်ဆုံးနဲ့ အညံ့ဆုံး ကျောင်းသားတွေကြားမှာ ဉာဏ်ရည် (IQ) တစ်ခုတည်းက ကွာခြားချက်မဟုတ်ပါဘူး။"
  },
  {
    "start": 45.194,
    "end": 49.745,
    "english": "Some of my strongest performers did not have stratospheric IQ scores.",
    "burmese": "အကောင်းဆုံး လုပ်ဆောင်နိုင်တဲ့ ကျောင်းသားတချို့မှာ ဉာဏ်ရည် (IQ) အရမ်းကောင်းတာမျိုး မရှိဘူး။"
  },
  {
    "start": 50.486,
    "end": 53.553,
    "english": "Some of my smartest kids weren't doing so well.",
    "burmese": "အတော်ဆုံးကလေးတချို့ကလည်း သိပ်အဆင်မပြေဘူးဖြစ်နေတယ်။"
  },
  {
    "start": 54.495,
    "end": 56.059,
    "english": "And that got me thinking,",
    "burmese": "အဲ့ဒီ့မှာ ကျွန်မတစ်ခုစဉ်းစားမိတယ်။"
  },
  {
    "start": 56.512,
    "end": 60.879,
    "english": " The kinds of things you need to learn in seventh grade math, sure, they're hard.",
    "burmese": "သတ္တမတန်း သင်္ချာမှာ သင်ယူရတဲ့အရာတွေက တကယ်တော့ ခက်ပါတယ်။"
  },
  {
    "start": 64.725,
    "end": 66.748,
    "english": "But these concepts are not impossible.",
    "burmese": "ဒါပေမဲ့ ဒီသင်ယူရမဲ့အရာတွေက မဖြစ်နိုင်တဲ့အရာတွေတော့မဟုတ်ပါဘူး။"
  },
  {
    "start": 67.55,
    "end": 73.539,
    "english": "And I was firmly convinced that every one of my students could learn the material",
    "burmese": "ကျွန်မရဲ့ ကျောင်းသားတိုင်းဟာ ဒီအကြောင်းအရာတွေကို သင်ယူနိုင်လိမ့်မယ်လို့ ကျွန်မ ခိုင်ခိုင်မာမာ ယုံကြည်ခဲ့တယ်။"
  },
  {
    "start": 73.579,
    "end": 75.603,
    "english": "if they worked hard and long enough.",
    "burmese": "သူတို့တွေကကြိုးစားပြီး လုံလောက်တဲ့အချိန်ပေးမယ်ဆိုရင်ပေါ့။"
  },
  {
    "start": 77.045,
    "end": 80.683,
    "english": "After several more years of teaching, I came to the conclusion.",
    "burmese": "နောက်ထပ် နှစ်အတော်ကြာ သင်ကြားပြီးတဲ့နောက်မှာ ကျွန်မကောက်ချက်ချလိုက်တယ်။"
  },
  {
    "start": 91.955,
    "end": 97.0,
    "english": "In education, the one thing we know how to measure best is IQ.",
    "burmese": "ပညာရေးမှာ ကျွန်မတို့ အကောင်းဆုံး တိုင်းတာနိုင်တဲ့အရာက ဉာဏ်ရည် (IQ) ပဲ ဖြစ်ပါတယ်။"
  },
  {
    "start": 98.261,
    "end": 107.511,
    "english": "But what if doing well in school and in life depends on much more than your ability to learn quickly and easily?",
    "burmese": "ဒါပေမဲ့ ပညာရေးမှာရော ဘဝမှာ‌ပါ အောင်မြင်ဖို့ဆိုတာ လွယ်ကူပြီး မြန်မြန်ဆန်ဆန် သင်ယူတတ်တဲ့ အရည်အချင်းထက် ပိုပြီးအရေးပါတဲ့အရာတွေပေါ်မှာ မူတည်နေရင်‌ရော ဘယ်လိုလုပ်မလဲ။"
  },
  {
    "start": 108.47,
    "end": 112.994,
    "english": "So I left the classroom and I went to graduate school to become a psychologist.",
    "burmese": "ဒါကြောင့် ကျွန်မ ဆရာမအလုပ်ကို စွန့်ပြီး စိတ်ပညာရှင်တစ်ယောက်ဖြစ်ဖို့ ဘွဲ့လွန်ကျောင်း တက်ခဲ့တယ်။"
  },
  {
    "start": 114.055,
    "end": 118.5,
    "english": "I started studying kids and adults in all kinds of super challenging settings.",
    "burmese": "အဲဒီမှာ အရမ်းကို စိန်ခေါ်မှုများတဲ့ ပတ်ဝန်းကျင်အမျိုးမျိုးက ကလေးတွေနဲ့ လူကြီးတွေကို စပြီး လေ့လာခဲ့တယ်။"
  },
  {
    "start": 119.22,
    "end": 123.485,
    "english": "and In every study,My question was who is successful here and why?,",
    "burmese": "လေ့လာမှုတိုင်းမှာ ကျွန်မရဲ့မေးခွန်းကတော့ ဒီနေရာမှာ ဘယ်သူက အောင်မြင်ပြီး ဘာကြောင့်‌အောင်မြင်နေလဲ ဆိုတာပါပဲ။"
  },
  {
    "start": 123.505,
    "end": 127.889,
    "english": "My research team and I went to West Point Military Academy.",
    "burmese": "ကျွန်မရဲ့ သုတေသနအဖွဲ့နဲ့ ကျွန်မဟာ West Point စစ်တက္ကသိုလ်ကို သွားခဲ့တယ်။"
  },
  {
    "start": 128.59,
    "end": 134.275,
    "english": "We tried to predict which cadets would stay in military training and which would drop out.",
    "burmese": "ဘယ်တပ်သားတွေက စစ်သင်တန်းမှာ ဆက်နေပြီး ဘယ်တပ်သားတွေက ထွက်သွားမယ်ဆိုတာ ကြိုတင်ခန့်မှန်းဖို့ ကြိုးစားခဲ့တယ်။"
  },
  {
    "start": 134.508,
    "end": 140.916,
    "english": "We went to the National Spelling Bee and tried to predict which children would advance farthest in competition.",
    "burmese": "ကျွန်မတို့တွေ National Spelling Bee ပြိုင်ပွဲကို သွားပြီး ဘယ်ကလေးတွေက ပြိုင်ပွဲမှာ အမြင့်ဆုံး တက်လှမ်းနိုင်မလဲဆိုတာ ကြိုတင်ခန့်မှန်းဖို့ ကြိုးစားခဲ့ကြတယ်။"
  },
  {
    "start": 142.037,
    "end": 145.582,
    "english": "We studied rookie teachers working in really tough neighborhoods.",
    "burmese": "အရမ်းခက်ခဲတဲ့ ရပ်ကွက်တွေမှာ အလုပ်လုပ်နေတဲ့ ဆရာ/ဆရာမအသစ်တွေကို ကျွန်မတို့လေ့လာခဲ့ကြတယ်။"
  },
  {
    "start": 151.609,
    "end": 156.936,
    "english": "and of those who will be the most effective at improving learning outcomes for their students.",
    "burmese": "ပြီးတော့ အဲ့ဒီ့ထဲက ဘယ်သူတွေက သူတို့ကျောင်းသားတွေရဲ့ သင်ယူမှုရလဒ်တွေကို ပိုပြီးကောင်းမွန်အောင် လုပ်နိုင်မလဲ ဆိုတာကိုလည်း လေ့လာခဲ့တယ်။"
  },
  {
    "start": 157.737,
    "end": 162.142,
    "english": "We partnered with private companies asking which of these salespeople is gonna keep their jobs?",
    "burmese": "ပုဂ္ဂလိကကုမ္ပဏီတွေနဲ့လည်း လက်တွဲပြီး ဒီအရောင်းသမားတွေထဲက ဘယ်သူတွေက သူတို့အလုပ်ကို ဆက်လုပ်နိုင်မလဲဆိုတာကို မေးခွန်းထုတ်ခဲ့ကြတယ်။"
  },
  {
    "start": 164.849,
    "end": 171.764,
    "english": "In all those very different contexts, one characteristic emerged as a significant predictor of success.",
    "burmese": "ဒီလိုမတူညီတဲ့ အခြေအနေအားလုံးမှာ အောင်မြင်မှုကို ခန့်မှန်းနိုင်တဲ့ အရေးကြီးတဲ့လက္ခဏာတစ်ခု ပေါ်ထွက်လာခဲ့တယ်။"
  },
  {
    "start": 164.849,
    "end": 171.764,
    "english": "And it wasn't social intelligence, it wasn't good looks,physical health, and it wasn't IQ.",
    "burmese": "အဲ့တာက လူမှုဆက်ဆံရေး ဉာဏ်ရည်မဟုတ်ဘူး။ ရုပ်ရည်၊ ကိုယ်ခန္ဓာကျန်းမာရေးလဲမဟုတ်ဘူး။ ဉာဏ်ရည် (IQ) လဲမဟုတ်ပါဘူး။ "
  },
  {
    "start": 178.799,
    "end": 180.883,
    "english": "It was grit.",
    "burmese": "အဲ့တာက 'Grit (စိတ်ဓာတ်ကြံ့ခိုင်ခြင်း)' ပါ။"
  },
  {
    "start": 182.028,
    "end": 186.353,
    "english": "Grit is passion and perseverance for very long-term goals.",
    "burmese": "Grit ဆိုတာဟာ ရေရှည်ပန်းတိုင်တွေအတွက် စိတ်အားထက်သန်မှုနဲ့ ဇွဲရှိမှုပဲ ဖြစ်ပါတယ်။"
  },
  {
    "start": 187.154,
    "end": 188.615,
    "english": "Grit is having stamina.",
    "burmese": "Gritဆိုတာဟာ ခံနိုင်ရည်ရှိတာပါ။"
  },
  {
    "start": 189.356,
    "end": 196.263,
    "english": "Grit is sticking with your future  day in, day out, not just for the week,not just for the month.",
    "burmese": "Grit ဆိုတာဟာ သင်ရဲ့အနာဂတ်ကို တစ်နေ့ပြီးတစ်နေ့၊ တစ်ပတ်ပြီးတစ်ပတ်၊ တစ်လပြီးတစ်လ မဆုတ်မနစ် ဆက်လက်လုပ်ဆောင်ခြင်းဖြစ်တယ်။"
  },
  {
    "start": 203.151,
    "end": 207.175,
    "english": "Grit is living life like it's a marathon, not a sprint.",
    "burmese": "Grit ဆိုတာ ဘဝကို မာရသွန်ပြေးပွဲလို နေထိုင်တာပါ၊ တာတိုပြေးပြိုင်ပွဲလို နေထိုင်တာ မဟုတ်ပါဘူး။"
  },
  {
    "start": 208.302,
    "end": 212.373,
    "english": "A few years ago I started studying grit in the Chicago public schools.",
    "burmese": "လွန်ခဲ့တဲ့ နှစ်အနည်းငယ်က ကျွန်မဟာ ချီကာဂိုမှာရှိတဲ့ အစိုးရကျောင်းတွေမှာ Grit ကို စပြီးလေ့လာခဲ့တယ်။"
  },
  {
    "start": 213.296,
    "end": 216.926,
    "english": "I asked thousands of high school juniors to take grit questionnaires.",
    "burmese": "ထောင်နဲ့ချီတဲ့ အထက်တန်းကျောင်းသားလေးတွေကို Grit မေးခွန်းလွှာတွေ ဖြေခိုင်းခဲ့တယ်။"
  },
  {
    "start": 217.587,
    "end": 220.776,
    "english": "And then waited around more than a year to see who would graduate.",
    "burmese": "ပြီးတော့ ဘယ်သူတွေက ဘွဲ့ရမလဲဆိုတာကို တစ်နှစ်ကျော်ကျော် စောင့်ကြည့်ခဲ့တယ်။"
  },
  {
    "start": 221.617,
    "end": 226.424,
    "english": "Turns out that grittier kids were significantly more likely to graduate.",
    "burmese": "စိတ်ဓာတ်ကြံ့ခိုင်မှု (Grit)ပိုရှိတဲ့ ကလေးတွေက ဘွဲ့ရဖို့ သိသိသာသာ ပိုများတယ်လို့ တွေ့ရပါတယ်။"
  },
  {
    "start": 239.543,
    "end": 243.048,
    "english": "So it's not just at West Point or the National Spelling Bee that grit matters.",
    "burmese": "ဒါကြောင့် စိတ်ဓာတ်ကြံ့ခိုင်မှုဟာ West Point နဲ့ National Spelling Bee မှာပဲ အရေးကြီးတာ မဟုတ်ပါဘူး။"
  },
  {
    "start": 243.629,
    "end": 247.995,
    "english": "It's also in school.Especially for kids at risk for dropping out.",
    "burmese": "ကျောင်းမှာလဲ အရေးကြီးပါတယ်။"
  },
  {
    "start": 249.241,
    "end": 253.569,
    "english": "To me, the most shocking thing about grit is how little we know.",
    "burmese": "ကျွန်မအတွက်တော့ စိတ်ဓာတ်ကြံ့ခိုင်မှုနဲ့ပတ်သက်ပြီး ထိတ်လန့်စရာကောင်းတဲ့အရာက ကျွန်မတို့ ဘယ်လောက်ထိ နားလည်ကြသလဲဆိုတာနဲ့။"
  },
  {
    "start": 253.609,
    "end": 256.454,
    "english": "how little science knows about building it.",
    "burmese": "ဒါကို ဘယ်လိုတည်ဆောက်ရမလဲဆိုတာပါပဲ "
  },
  {
    "start": 257.236,
    "end": 261.223,
    "english": "Every day, parents and teachers ask me, how do I build grit in kids?",
    "burmese": "နေ့တိုင်း မိဘတွေနဲ့ ဆရာတွေက ကလေးတွေမှာ စိတ်ဓာတ်ကြံ့ခိုင်မှုကို ဘယ်လိုတည်ဆောက်ရမလဲ လို့ ကျွန်မကို မေးကြတယ်။"
  },
  {
    "start": 261.664,
    "end": 264.409,
    "english": "What do I do to teach kids a solid work ethic?",
    "burmese": "ကလေးတွေကို ခိုင်မာတဲ့ အလုပ်ကျင့်ဝတ်တစ်ခု ဘယ်လိုသင်ပေးရမလဲ"
  },
  {
    "start": 264.87,
    "end": 266.974,
    "english": "How do I keep them motivated for the long run?",
    "burmese": "ရေရှည်အတွက် သူတို့ကို ဘယ်လို စိတ်အားထက်သန်အောင် ထားရမလဲ"
  },
  {
    "start": 267.014,
    "end": 270.861,
    "english": "The honest answer is I don't know.",
    "burmese": "ရိုးရိုးသားသားပြောရရင် ကျွန်မ မသိသေးပါဘူး။"
  },
  {
    "start": 272.562,
    "end": 274.966,
    "english": "What I do know is that talent doesn't make you gritty.",
    "burmese": "ကျွန်မသိတာကတော့ အရည်အချင်းရှိရုံနဲ့ စိတ်ဓာတ်ကြံ့ခိုင်တာ မဟုတ်ပါဘူး။"
  },
  {
    "start": 275.006,
    "end": 283.238,
    "english": "Our data show very clearly that there are many talented individuals who simply do not follow through on their commitments.",
    "burmese": "ကျွန်မတို့ရဲ့ အချက်အလက်တွေက အရည်အချင်းရှိတဲ့သူ အများစုဟာ သူတို့ရဲ့ ဆုံးဖြတ်ထားပြီးသားကိစ္စတွေကို ဆက်လက်မလုပ်ဆောင်ကြဘူးဆိုတာကို ရှင်းရှင်းလင်းလင်း ပြသနေပါတယ်။"
  },
  {
    "start": 283.979,
    "end": 291.33,
    "english": "In fact, in our data, grit is usually unrelated or even inversely related to measures of talent.",
    "burmese": "တကယ်တော့ ကျွန်မတို့ရဲ့ အချက်အလက်တွေမှာ စိတ်ဓာတ်ကြံ့ခိုင်မှုဟာ အရည်အချင်း တိုင်းတာမှုတွေနဲ့ မသက်ဆိုင်ဘူး၊ ဒါမှမဟုတ် ဆန့်ကျင်ဘက်တောင် ဖြစ်နေတတ်ပါတယ်။"
  },
  {
    "start": 292.542,
    "end": 298.691,
    "english": "So far, the best idea I've heard about building grit in kids is something called growth mindset.",
    "burmese": "ခုချိန်အထိ ကလေးတွေမှာ စိတ်ဓာတ်ကြံ့ခိုင်မှုတည်ဆောက်ဖို့အတွက် ကျွန်မ ကြားဖူးသမျှ အကောင်းဆုံး အယူအဆက 'growth mindset' လို့ခေါ်တဲ့ အရာတစ်ခုပါ။"
  },
  {
    "start": 299.573,
    "end": 302.778,
    "english": "This is an idea developed at Stanford University by Carol Dweck.",
    "burmese": "ဒါက စတန့်ဖို့ဒ်တက္ကသိုလ်က Carol Dweck ကနေ တီထွင်ခဲ့တဲ့ အယူအဆတစ်ခုဖြစ်ပါတယ်။"
  },
  {
    "start": 329.296,
    "end": 334.03,
    "english": "So growth mindset is a great idea for building grit, but we need more.",
    "burmese": "ဒါကြောင့် growth mindset ဟာ စိတ်ဓာတ်ကြံ့ခိုင်မှုကို တည်ဆောက်ဖို့အတွက် ကောင်းမွန်တဲ့ အယူအဆတစ်ခုဖြစ်ပါတယ် ဒါပေမဲ့ ကျွန်မတို့ ပိုပြီးလိုအပ်နေပါသေးတယ်။"
  },
  {
    "start": 334.09,
    "end": 337.874,
    "english": "And that's where I'm gonna end my remarks because that's where we are.",
    "burmese": "အဲဒီ့အချက်နဲ့ပဲ ကျွန်မရဲ့ စကားကို အဆုံးသတ်ပါမယ်။ ဘာလို့ဆို အဲဒီ့အဆင့်မှာပဲ ကျွန်မတို့ ရှိနေသေးလို့ပါ။"
  },
  {
    "start": 338.274,
    "end": 340.176,
    "english": "That's the work that stands before us.",
    "burmese": "အဲ့တာဟာ ကျွန်မတို့ရှေ့မှာ ရပ်နေတဲ့ အလုပ်ပဲဖြစ်ပါတယ်။"
  },
  {
    "start": 340.696,
    "end": 345.981,
    "english": "We need to take our best ideas, our strongest intuitions, and we need to test them.",
    "burmese": "ကျွန်မတို့ရဲ့ အကောင်းဆုံး အယူအဆတွေ၊ အခိုင်မာဆုံး အတွေးအမြင်တွေကို လိုပါတယ်။ပြီးတော့ စမ်းသပ်ကြည့်ဖို့လိုပါသေးတယ်။"
  },
  {
    "start": 346.621,
    "end": 348.903,
    "english": "We need to measure whether we've been successful",
    "burmese": "ကျွန်မတို့ အောင်မြင်ခဲ့သလားဆိုတာကို တိုင်းတာဖို့ လိုအပ်ပါတယ်။"
  },
  {
    "start": 349.404,
    "end": 355.449,
    "english": "and we have to be willing to fail to be wrong, to start over again with lessons learned.",
    "burmese": "ပြီးတော့ ကျရှုံးဖို့၊ မှားယွင်းဖို့၊ သင်ခန်းစာတွေနဲ့အတူ အစကနေ ပြန်စဖို့လည်း ဆန္ဒရှိရပါမယ်။"
  },
  {
    "start": 356.57,
    "end": 362.155,
    "english": "In other words, we need to be gritty about getting our kids grittier.",
    "burmese": "တစ်နည်းပြောရရင် ကျွန်မတို့ရဲ့ကလေးတွေ ပိုပြီးဇွဲရှိလာအောင်လုပ်ဖို့ ကျွန်မတို့ကိုယ်တိုင် ဇွဲရှိဖို့ လိုအပ်ပါတယ်။"
  }
]
